{
  "generated_at": "2026-07-02 00:23:31 UTC",
  "total_streams": 16474,
  "online_streams": 11805,
  "offline_streams": 4669,
  "online_percent": 71.7,
  "categories": 30,
  "countries": 171,
  "languages": 113,
  "by_source": {
    "iptv-org": {
      "total": 16474,
      "online": 11805
    }
  },
  "top_categories": [
    {
      "name": "Uncategorized",
      "online": 2818
    },
    {
      "name": "General",
      "online": 2187
    },
    {
      "name": "News",
      "online": 1194
    },
    {
      "name": "Entertainment",
      "online": 823
    },
    {
      "name": "Music",
      "online": 706
    },
    {
      "name": "Series",
      "online": 706
    },
    {
      "name": "Religious",
      "online": 660
    },
    {
      "name": "Movies",
      "online": 603
    },
    {
      "name": "Sports",
      "online": 405
    },
    {
      "name": "Kids",
      "online": 376
    },
    {
      "name": "Documentary",
      "online": 264
    },
    {
      "name": "Comedy",
      "online": 257
    },
    {
      "name": "Animation",
      "online": 176
    },
    {
      "name": "Education",
      "online": 166
    },
    {
      "name": "Culture",
      "online": 159
    },
    {
      "name": "Legislative",
      "online": 140
    },
    {
      "name": "Lifestyle",
      "online": 131
    },
    {
      "name": "Classic",
      "online": 106
    },
    {
      "name": "Business",
      "online": 101
    },
    {
      "name": "Outdoor",
      "online": 100
    }
  ]
}