{
  "generated_at": "2026-07-01 16:42:18 UTC",
  "total_streams": 16474,
  "online_streams": 11774,
  "offline_streams": 4700,
  "online_percent": 71.5,
  "categories": 30,
  "countries": 171,
  "languages": 113,
  "by_source": {
    "iptv-org": {
      "total": 16474,
      "online": 11774
    }
  },
  "top_categories": [
    {
      "name": "Uncategorized",
      "online": 2826
    },
    {
      "name": "General",
      "online": 2177
    },
    {
      "name": "News",
      "online": 1202
    },
    {
      "name": "Entertainment",
      "online": 813
    },
    {
      "name": "Series",
      "online": 708
    },
    {
      "name": "Music",
      "online": 696
    },
    {
      "name": "Religious",
      "online": 659
    },
    {
      "name": "Movies",
      "online": 601
    },
    {
      "name": "Sports",
      "online": 404
    },
    {
      "name": "Kids",
      "online": 377
    },
    {
      "name": "Documentary",
      "online": 262
    },
    {
      "name": "Comedy",
      "online": 258
    },
    {
      "name": "Animation",
      "online": 178
    },
    {
      "name": "Education",
      "online": 160
    },
    {
      "name": "Culture",
      "online": 155
    },
    {
      "name": "Legislative",
      "online": 137
    },
    {
      "name": "Lifestyle",
      "online": 128
    },
    {
      "name": "Classic",
      "online": 104
    },
    {
      "name": "Business",
      "online": 102
    },
    {
      "name": "Outdoor",
      "online": 97
    }
  ]
}