{
  "generated_at": "2026-06-27 19:54:02 UTC",
  "total_streams": 16675,
  "online_streams": 11993,
  "offline_streams": 4682,
  "online_percent": 71.9,
  "categories": 29,
  "countries": 169,
  "languages": 109,
  "by_source": {
    "iptv-org": {
      "total": 16675,
      "online": 11993
    }
  },
  "top_categories": [
    {
      "name": "Uncategorized",
      "online": 3267
    },
    {
      "name": "General",
      "online": 2161
    },
    {
      "name": "News",
      "online": 1204
    },
    {
      "name": "Music",
      "online": 718
    },
    {
      "name": "Entertainment",
      "online": 702
    },
    {
      "name": "Religious",
      "online": 647
    },
    {
      "name": "Series",
      "online": 624
    },
    {
      "name": "Movies",
      "online": 588
    },
    {
      "name": "Sports",
      "online": 460
    },
    {
      "name": "Kids",
      "online": 372
    },
    {
      "name": "Documentary",
      "online": 281
    },
    {
      "name": "Education",
      "online": 161
    },
    {
      "name": "Culture",
      "online": 156
    },
    {
      "name": "Comedy",
      "online": 144
    },
    {
      "name": "Legislative",
      "online": 139
    },
    {
      "name": "Animation",
      "online": 128
    },
    {
      "name": "Lifestyle",
      "online": 127
    },
    {
      "name": "Business",
      "online": 100
    },
    {
      "name": "Outdoor",
      "online": 98
    },
    {
      "name": "Shop",
      "online": 83
    }
  ]
}